pycroner/__init__.py
pycroner/__main__.py
pycroner/check.py
pycroner/cli_colors.py
pycroner/load.py
pycroner/logger.py
pycroner/models.py
pycroner/parser.py
pycroner/printer.py
pycroner/runner.py
pycroner-0.1.9.dist-info/licenses/LICENSE
pycroner-0.1.9.dist-info/METADATA
pycroner-0.1.9.dist-info/WHEEL
pycroner-0.1.9.dist-info/entry_points.txt
pycroner-0.1.9.dist-info/top_level.txt
pycroner-0.1.9.dist-info/RECORD
