Metadata-Version: 2.4
Name: pycroner
Version: 0.1.9
Summary: A multi-platform cron-like job runner in Python
Author-email: Marin Luic <marin.luic@gmail.com>
License-Expression: GPL-3.0
Project-URL: Homepage, https://github.com/AcidBurnHen/pycroner
Project-URL: Repository, https://github.com/AcidBurnHen/pycroner
Classifier: Programming Language :: Python :: 3
Classifier: Programming Language :: Python :: 3.8
Classifier: Programming Language :: Python :: 3.9
Classifier: Operating System :: OS Independent
Classifier: Environment :: Console
Classifier: Intended Audience :: Developers
Classifier: Topic :: System :: Systems Administration
Classifier: Topic :: Utilities
Requires-Python: >=3.8
License-File: LICENSE
Requires-Dist: pyyaml>=6.0
Dynamic: license-file
